[
	{
		"inputs": [],
		"stateMutability": "nonpayable",
		"type": "constructor"
	},
	{
		"anonymous": false,
		"inputs": [
			{
				"indexed": true,
				"internalType": "address",
				"name": "player",
				"type": "address"
			},
			{
				"indexed": false,
				"internalType": "uint256",
				"name": "bet",
				"type": "uint256"
			}
		],
		"name": "BetPlaced",
		"type": "event"
	},
	{
		"inputs": [
			{
				"internalType": "enum CoinflipGame.Choice",
				"name": "_choice",
				"type": "uint8"
			}
		],
		"name": "flipCoin",
		"outputs": [],
		"stateMutability": "payable",
		"type": "function"
	},
	{
		"anonymous": false,
		"inputs": [
			{
				"indexed": true,
				"internalType": "address",
				"name": "player",
				"type": "address"
			},
			{
				"indexed": false,
				"internalType": "enum CoinflipGame.Choice",
				"name": "playerChoice",
				"type": "uint8"
			},
			{
				"indexed": false,
				"internalType": "bool",
				"name": "result",
				"type": "bool"
			},
			{
				"indexed": false,
				"internalType": "bool",
				"name": "won",
				"type": "bool"
			},
			{
				"indexed": false,
				"internalType": "uint256",
				"name": "amount",
				"type": "uint256"
			},
			{
				"indexed": false,
				"internalType": "uint256",
				"name": "bet",
				"type": "uint256"
			},
			{
				"indexed": false,
				"internalType": "bytes32",
				"name": "requestId",
				"type": "bytes32"
			}
		],
		"name": "FlipResult",
		"type": "event"
	},
	{
		"inputs": [],
		"name": "fundGamePool",
		"outputs": [],
		"stateMutability": "payable",
		"type": "function"
	},
	{
		"anonymous": false,
		"inputs": [
			{
				"indexed": true,
				"internalType": "address",
				"name": "depositor",
				"type": "address"
			},
			{
				"indexed": false,
				"internalType": "uint256",
				"name": "amount",
				"type": "uint256"
			},
			{
				"indexed": false,
				"internalType": "uint256",
				"name": "toGamePool",
				"type": "uint256"
			},
			{
				"indexed": false,
				"internalType": "uint256",
				"name": "toReserve",
				"type": "uint256"
			}
		],
		"name": "FundsDeposited",
		"type": "event"
	},
	{
		"anonymous": false,
		"inputs": [
			{
				"indexed": true,
				"internalType": "address",
				"name": "owner",
				"type": "address"
			},
			{
				"indexed": false,
				"internalType": "uint256",
				"name": "amount",
				"type": "uint256"
			},
			{
				"indexed": false,
				"internalType": "bool",
				"name": "toGamePool",
				"type": "bool"
			}
		],
		"name": "FundsMoved",
		"type": "event"
	},
	{
		"anonymous": false,
		"inputs": [
			{
				"indexed": true,
				"internalType": "address",
				"name": "recipient",
				"type": "address"
			},
			{
				"indexed": false,
				"internalType": "uint256",
				"name": "amount",
				"type": "uint256"
			}
		],
		"name": "FundsWithdrawn",
		"type": "event"
	},
	{
		"inputs": [
			{
				"internalType": "uint256",
				"name": "amount",
				"type": "uint256"
			}
		],
		"name": "moveFromGamePool",
		"outputs": [],
		"stateMutability": "nonpayable",
		"type": "function"
	},
	{
		"inputs": [
			{
				"internalType": "uint256",
				"name": "amount",
				"type": "uint256"
			}
		],
		"name": "moveToGamePool",
		"outputs": [],
		"stateMutability": "nonpayable",
		"type": "function"
	},
	{
		"inputs": [],
		"name": "withdrawAllFunds",
		"outputs": [],
		"stateMutability": "nonpayable",
		"type": "function"
	},
	{
		"stateMutability": "payable",
		"type": "receive"
	},
	{
		"inputs": [],
		"name": "contractBalance",
		"outputs": [
			{
				"internalType": "uint256",
				"name": "",
				"type": "uint256"
			}
		],
		"stateMutability": "view",
		"type": "function"
	},
	{
		"inputs": [],
		"name": "gamePool",
		"outputs": [
			{
				"internalType": "uint256",
				"name": "",
				"type": "uint256"
			}
		],
		"stateMutability": "view",
		"type": "function"
	},
	{
		"inputs": [],
		"name": "getContractBalance",
		"outputs": [
			{
				"internalType": "uint256",
				"name": "",
				"type": "uint256"
			}
		],
		"stateMutability": "view",
		"type": "function"
	},
	{
		"inputs": [],
		"name": "getTotalBalance",
		"outputs": [
			{
				"internalType": "uint256",
				"name": "",
				"type": "uint256"
			}
		],
		"stateMutability": "view",
		"type": "function"
	},
	{
		"inputs": [],
		"name": "MIN_BET",
		"outputs": [
			{
				"internalType": "uint256",
				"name": "",
				"type": "uint256"
			}
		],
		"stateMutability": "view",
		"type": "function"
	},
	{
		"inputs": [],
		"name": "owner",
		"outputs": [
			{
				"internalType": "address",
				"name": "",
				"type": "address"
			}
		],
		"stateMutability": "view",
		"type": "function"
	}
]